xkcd/__init__.py
xkcd/main.py
cli_xkcd-1.0.4.dist-info/METADATA
cli_xkcd-1.0.4.dist-info/WHEEL
cli_xkcd-1.0.4.dist-info/entry_points.txt
cli_xkcd-1.0.4.dist-info/top_level.txt
cli_xkcd-1.0.4.dist-info/RECORD
