Metadata-Version: 2.1
Name: cli-xkcd
Version: 1.0.4
Summary: See the daily xkcd comic from your terminal.
Home-page: https://github.com/bradendubois/xkcd
Author: Braden Dubois
Author-email: braden.dubois@cs.usask.ca
License: UNKNOWN
Keywords: xkcd comic terminal beautifulsoup
Platform: UNKNOWN
Requires-Dist: bs4
